{"stats":{"minecraft:killed":{"mutant_entities:mutant_creeper":1,"minecraft:skeleton":2,"minecraft:pillager":3,"minecraft:spider":1,"alexsmobs:rhinoceros":1,"minecraft:creeper":11},"minecraft:crafted":{"minecraft:stone_brick_wall":6,"minecraft:torch":32},"minecraft:dropped":{"minecraft:spruce_planks":1,"minecraft:deepslate":172,"minecraft:phantom_membrane":1,"minecraft:stone_brick_stairs":1,"minecraft:grass_block":2},"minecraft:mined":{"minecraft:tuff":76,"minecraft:deepslate_diamond_ore":6,"minecraft:deepslate_lapis_ore":2,"minecraft:deepslate_iron_ore":1,"minecraft:gravel":148,"minecraft:stone_bricks":15,"minecraft:deepslate":868,"minecraft:deepslate_redstone_ore":8},"minecraft:used":{"waystones:waystone":1,"minecraft:oak_log":102,"minecraft:oak_trapdoor":91,"minecraft:iron_bars":6,"minecraft:netherite_shovel":148,"minecraft:spruce_door":5,"minecraft:grass_block":600,"minecraft:spruce_slab":146,"minecraft:baked_potato":7,"minecraft:oak_sign":1,"minecraft:spruce_planks":312,"minecraft:spruce_trapdoor":312,"minecraft:stone":92,"minecraft:deepslate":117,"minecraft:spruce_fence_gate":8,"gobber2:gobber2_hammer":889,"minecraft:stone_brick_stairs":335,"minecraft:stone_bricks":5542,"minecraft:deepslate_bricks":274,"minecraft:torch":282,"bosses_of_mass_destruction:monolith_block":2,"ageofweapons:claymore_netherite":33,"minecraft:anvil":1,"ageofweapons:multi_tool_netherite":15,"minecraft:spruce_stairs":125,"bosses_of_mass_destruction:levitation_block":4,"minecraft:andesite":98,"bosses_of_mass_destruction:charged_ender_pearl":9,"minecraft:deepslate_brick_slab":355,"deeperdarker:warden_pickaxe":72,"minecraft:tuff":15,"minecraft:stone_brick_wall":144,"minecraft:spruce_fence":14,"minecraft:deepslate_brick_stairs":168,"minecraft:stripped_spruce_log":19,"minecraft:milk_bucket":1},"minecraft:custom":{"minecraft:time_since_rest":313888,"minecraft:waystone_activated":1,"minecraft:sprint_one_cm":429882,"minecraft:damage_taken":27,"minecraft:walk_one_cm":937443,"minecraft:interact_with_anvil":1,"minecraft:mob_kills":19,"minecraft:drop":10,"minecraft:damage_dealt":6451,"minecraft:swim_one_cm":124984,"minecraft:fly_one_cm":1933898,"minecraft:crouch_one_cm":16141,"minecraft:play_time":313888,"minecraft:sneak_time":10549,"minecraft:walk_under_water_one_cm":81487,"minecraft:jump":812,"minecraft:damage_resisted":12,"minecraft:leave_game":5,"minecraft:walk_on_water_one_cm":17226,"minecraft:time_since_death":313888,"minecraft:total_world_time":313888,"minecraft:fall_one_cm":6650},"minecraft:picked_up":{"minecraft:stick":4,"minecraft:torch":5,"minecraft:tuff":55,"minecraft:stone_brick_stairs":1,"minecraft:grass_block":1,"minecraft:gunpowder":8,"mutant_entities:enchanted_gunpowder":3,"minecraft:white_banner":1,"minecraft:stone_bricks":14,"minecraft:arrow":2,"minecraft:deepslate":306,"minecraft:wheat_seeds":1,"minecraft:cobbled_deepslate":255,"minecraft:spruce_planks":1,"minecraft:deepslate_diamond_ore":16,"minecraft:oak_sapling":8}},"DataVersion":3120}